devtools_ai/__init__.py
devtools_ai/appium.py
devtools_ai/selenium.py
devtools_ai/utils/__init__.py
devtools_ai/utils/selenium_core.py
devtools_ai-0.0.11.dist-info/LICENSE.md
devtools_ai-0.0.11.dist-info/METADATA
devtools_ai-0.0.11.dist-info/WHEEL
devtools_ai-0.0.11.dist-info/top_level.txt
devtools_ai-0.0.11.dist-info/RECORD
