Metadata-Version: 2.1
Name: devtools-ai
Version: 0.0.11
Summary: A package to bring ai to selenium scripts.
Home-page: https://github.com/dev-tools-ai/python-sdk
Author: Chris Navrides
Author-email: chris@dev-tools.ai
Project-URL: Bug Tracker, https://github.com/dev-tools-ai/python-sdk/issues
Classifier: Natural Language :: English
Classifier: Programming Language :: Python :: 3
Classifier: Programming Language :: Python :: 3.7
Classifier: Programming Language :: Python :: 3.8
Classifier: Programming Language :: Python :: 3.9
Classifier: Programming Language :: Python :: 3.10
Classifier: Intended Audience :: Developers
Classifier: License :: OSI Approved :: Apache Software License
Classifier: Operating System :: OS Independent
Classifier: Topic :: Software Development :: Testing
Classifier: Topic :: Software Development :: Quality Assurance
Classifier: Topic :: Software Development :: Testing :: Unit
Requires-Python: >=3.7
License-File: LICENSE.md
Requires-Dist: packaging
Requires-Dist: pillow
Requires-Dist: requests
Requires-Dist: selenium
Requires-Dist: Appium-Python-Client
